pyecoregen/__init__.py
pyecoregen/adapter.py
pyecoregen/cli.py
pyecoregen/ecore.py
pyecoregen/templates/mixins.py.skeleton.tpl
pyecoregen/templates/module.py.tpl
pyecoregen/templates/module_utilities.tpl
pyecoregen/templates/package.py.tpl
pyecoregen-0.5.1.dist-info/LICENSE
pyecoregen-0.5.1.dist-info/METADATA
pyecoregen-0.5.1.dist-info/WHEEL
pyecoregen-0.5.1.dist-info/entry_points.txt
pyecoregen-0.5.1.dist-info/top_level.txt
pyecoregen-0.5.1.dist-info/RECORD
