Metadata-Version: 1.1
Name: pyecoregen
Version: 0.5.1
Summary: Model to text framework for PyEcore, including the Ecore to Python generator
Home-page: https://github.com/pyecore/pyecoregen
Author: Mike Pagel
Author-email: mike@mpagel.de
License: BSD 3-Clause
Keywords: model metamodel EMF Ecore code generator
Platform: UNKNOWN
Classifier: Development Status :: 4 - Beta
Classifier: Programming Language :: Python
Classifier: Programming Language :: Python :: 3 :: Only
Classifier: Operating System :: OS Independent
Classifier: Intended Audience :: Developers
Classifier: Topic :: Software Development
Classifier: Topic :: Software Development :: Libraries
Classifier: License :: OSI Approved :: BSD License
